llama_index/readers/remote_depth/__init__.py
llama_index/readers/remote_depth/base.py
llama_index_readers_remote_depth-0.4.1.dist-info/METADATA
llama_index_readers_remote_depth-0.4.1.dist-info/WHEEL
llama_index_readers_remote_depth-0.4.1.dist-info/licenses/LICENSE
llama_index_readers_remote_depth-0.4.1.dist-info/RECORD
