Metadata-Version: 2.4
Name: llama-index-readers-remote-depth
Version: 0.4.1
Summary: llama-index readers remote_depth integration
Author-email: Your Name <you@example.com>
Maintainer: simonMoisselin
License-Expression: MIT
License-File: LICENSE
Keywords: hosted,multiple,url
Requires-Python: <3.12,>=3.9
Requires-Dist: llama-index-core<0.15,>=0.13.0
Requires-Dist: llama-index-readers-remote<0.5,>=0.4.0
